README.md
setup.py
AutoAiLib/__init__.py
AutoAiLib.egg-info/PKG-INFO
AutoAiLib.egg-info/SOURCES.txt
AutoAiLib.egg-info/dependency_links.txt
AutoAiLib.egg-info/requires.txt
AutoAiLib.egg-info/top_level.txt