Metadata-Version: 2.1
Name: AutoAiLib
Version: 1.0.5
Summary: The library that automates the silly ML things.
Home-page: UNKNOWN
Author: Matthew Mulhall
Author-email: matthewlmulhall@gmail.com
License: GNU GPLv3
Platform: UNKNOWN
Classifier: Programming Language :: Python :: 3
